SPRINT2/decodificador.sv
module decodificador(input logic [11:8] SW,
					 output logic [0:6] QQ);

	logic [0:6] HEX3;
	assign QQ = ~HEX3; // Deixar nível baixo, de acordo com ao FPGA utilizada no lab
				
	always_comb
		begin
			case(SW)
			4'h0:  HEX3 = 7'b1111110;
			4'h1:  HEX3 = 7'b0110000;
			4'h2:  HEX3 = 7'b1101101;
			4'h3:  HEX3 = 7'b1111001;
			4'h4:  HEX3 = 7'b0111011;
			4'h5:  HEX3 = 7'b1011011;
			4'h6:  HEX3 = 7'b1011111;
			4'h7:  HEX3 = 7'b1110000;
			4'h8:  HEX3 = 7'b1111111;
			4'h9:  HEX3 = 7'b1111011;
			4'hA:  HEX3 = 7'b1110111;
			4'hB:  HEX3 = 7'b0011111;
			4'hC:  HEX3 = 7'b1001110;
			4'hD:  HEX3 = 7'b0111101;
			4'hE:  HEX3 = 7'b1001111;
			4'hF:  HEX3 = 8'b1000111;
			endcase		
		end


endmodule

SPRINT2/tb_decodificador.sv
`include ".\decodificador.sv"

// testebench by Valmir Ferreira
module tb;
    logic [3:0] bincode;
    logic [6:0] pinoutdisplay7segment;
    logic [4:0] pass_fail, pass_test;

    decodificador display7segment(
        .SW  (            bincode          ),
        .QQ  (     pinoutdisplay7segment   )
    );

    task expect_output(
        input [6:0] pinoutdisplay7segment_expect);
        begin   
            if(pinoutdisplay7segment == pinoutdisplay7segment_expect)
                pass_test+=1;
            else begin
                pass_fail+=1;
                $display("%d %b %b",bincode,pinoutdisplay7segment,pinoutdisplay7segment_expect);
            end
        end
    endtask

    initial begin
        pass_fail = 0;
        pass_test = 0;
        $display("expected  : obtained");
        $dumpfile("decod_hex2_7seg.vcd");
        $dumpvars(0,display7segment);
        bincode = 0; #1expect_output(~7'b1111110);
        bincode = 1; #1expect_output(~7'b0110000);
        bincode = 2; #1expect_output(~7'b1101101);
        bincode = 3; #1expect_output(~7'b1111001);
        bincode = 4; #1expect_output(~7'b0111011);
        bincode = 5; #1expect_output(~7'b1011011);
        bincode = 6; #1expect_output(~7'b1011111);
        bincode = 7; #1expect_output(~7'b1110000);
        bincode = 8; #1expect_output(~7'b1111111);
        bincode = 9; #1expect_output(~7'b1111011);
        $display("pass : fail");
        $display("%d    : %d ",pass_test,pass_fail);
    end
endmodule

SPRINT2/decod_hex2_7seg.vcd
$date
	Tue Mar 28 14:32:18 2023
$end
$version
	Icarus Verilog
$end
$timescale
	1s
$end
$scope module tb $end
$scope module display7segment $end
$var wire 7 ! QQ [0:6] $end
$var wire 4 " SW [11:8] $end
$var reg 7 # HEX3 [0:6] $end
$upscope $end
$upscope $end
$enddefinitions $end
$comment Show the parameter values. $end
$dumpall
$end
#0
$dumpvars
b1111110 #
b0 "
b1 !
$end
#1
b1001111 !
b110000 #
b1 "
#2
b10010 !
b1101101 #
b10 "
#3
b110 !
b1111001 #
b11 "
#4
b1000100 !
b111011 #
b100 "
#5
b100100 !
b1011011 #
b101 "
#6
b100000 !
b1011111 #
b110 "
#7
b1111 !
b1110000 #
b111 "
#8
b0 !
b1111111 #
b1000 "
#9
b100 !
b1111011 #
b1001 "
