SPRINT2/Cont_M10.sv
module Cont_M10(input logic clk, rst,
				output logic [3:0] cont);

					 
	logic contador = 0;

	always@(posedge clk)
		begin
			if(contador <= 4'd9) begin
				contador = contador + 1;
				cont = contador;
			end
			else begin
				contador = 0;
				cont = contador;
			end
		end

endmodule

SPRINT2/tb_Cont_M10.sv
`include ".\Cont_M10.sv"

module tb_Cont_M10();
    // Input 
    logic clk, rst;
    // Outputs
    logic [3:0] cont;

    Cont_M10 contm10(.clk( clk ), .rst( rst ), .cont( cont ));

    initial 
        begin
            clk = 0;
            rst = 0;
        end

    always #1 clk = ~clk;

    // initial
    //     begin
    //         #2 cont = 4'd1;
    //         #2 cont = 4'd2;
    //         #2 cont = 4'd3;
    //         #2 cont = 4'd4;
    //         #2 cont = 4'd5;
    //         #2 cont = 4'd6;
    //         #2 cont = 4'd7;
    //         #2 cont = 4'd8;
    //         #2 cont = 4'd9;
    //         #2 rst = 1;
    //         #2 cont = 4'd1;
    //     end

        initial
        begin
            $dumpfile("Sprint2.vcd");
            $dumpvars(0, contm10);
        end

    initial
        #20 $finish;


endmodule

SPRINT2/Sprint2.vcd
$date
	Sun Mar 26 23:06:03 2023
$end
$version
	Icarus Verilog
$end
$timescale
	1s
$end
$scope module tb_Cont_M10 $end
$scope module contm10 $end
$var wire 1 ! clk $end
$var wire 1 " rst $end
$var reg 4 # cont [3:0] $end
$var reg 1 $ contador $end
$upscope $end
$upscope $end
$enddefinitions $end
$comment Show the parameter values. $end
$dumpall
$end
#0
$dumpvars
0$
bx #
0"
0!
$end
#1
b1 #
1$
1!
#2
0!
#3
b0 #
0$
1!
#4
0!
#5
b1 #
1$
1!
#6
0!
#7
b0 #
0$
1!
#8
0!
#9
b1 #
1$
1!
#10
0!
#11
b0 #
0$
1!
#12
0!
#13
b1 #
1$
1!
#14
0!
#15
b0 #
0$
1!
#16
0!
#17
b1 #
1$
1!
#18
0!
#19
b0 #
0$
1!
