SPRINT2/decodificador.sv
module decodificador(input logic [11:8] SW,
					 output logic [0:6] HEX3);
							
							
	always_comb
		begin
			case(SW)
			4'h0:  HEX3 = 7'b0000000;
			4'h1:  HEX3 = 7'b1111110;
			4'h2:  HEX3 = 7'b0110000;
			4'h3:  HEX3 = 7'b1111001;
			4'h4:  HEX3 = 7'b0110011;
			4'h5:  HEX3 = 7'b1011011;
			4'h6:  HEX3 = 7'b1011111;
			4'h7:  HEX3 = 7'b1110000;
			4'h8:  HEX3 = 7'b1111111;
			4'h9:  HEX3 = 7'b1111011;
			4'hA:  HEX3 = 7'b1110111;
			4'hB:  HEX3 = 7'b0011111;
			4'hC:  HEX3 = 7'b1001110;
			4'hD:  HEX3 = 7'b0111101;
			4'hE:  HEX3 = 7'b1001111;
			4'hF:  HEX3 = 8'b1000111;
			endcase		
		end


endmodule

/*
case(A)
			4'h1:  HEX[2:1] = 1;
			4'h2: (HEX[1:0] && HEX[4:3] && HEX[0]) = 1;
			4'h3: (HEX[3:0] && HEX[6]) = 1;
			4'h4:  HEX[2:1] = 1;
			4'h5:  HEX[2:1] = 1;
			4'h6:  HEX[2:1] = 1;
			4'h7:  HEX[2:1] = 1;
			4'h8:  HEX[2:1] = 1;
			4'h9:  HEX[2:1] = 1;
			4'hA:  HEX[2:1] = 1;
			4'hB:  HEX[2:1] = 1;
			4'hC:  HEX[2:1] = 1;
			4'hD:  HEX[2:1] = 1;
			4'hE:  HEX[2:1] = 1;
			4'hF:  HEX[2:1] = 1;
			endcase
*/

SPRINT2/tb.sv
`include ".\decodificador.sv"

module tb();
    //Inputs
    logic [3:0] SW;
    //Outputs
    logic [0:6] HEX3;

    decodificador decod(.SW( SW ), .HEX3( HEX3 ));

    initial 
        begin
            SW = 4'h0;
        end

    initial
        begin
            #2 SW = 4'h1;
            #2 SW = 4'h2;
            #2 SW = 4'h3;
            #2 SW = 4'h4;
            #2 SW = 4'h5;
            #2 SW = 4'h6;
            #2 SW = 4'h7;
            #2 SW = 4'h8;
            #2 SW = 4'h9;
            #2 SW = 4'hA;
            #2 SW = 4'hB;
            #2 SW = 4'hC;
            #2 SW = 4'hD;
            #2 SW = 4'hE;
            #2 SW = 4'hF;
        end

    initial
        begin
            $dumpfile("Sprint2.vcd");
            $dumpvars(0, decod);
        end
    
    initial
        #30 $finish;


endmodule

SPRINT2/Sprint2.vcd
$date
	Sat Mar 25 20:45:59 2023
$end
$version
	Icarus Verilog
$end
$timescale
	1s
$end
$scope module tb $end
$scope module decod $end
$var wire 4 ! SW [11:8] $end
$var reg 7 " HEX3 [0:6] $end
$upscope $end
$upscope $end
$enddefinitions $end
$comment Show the parameter values. $end
$dumpall
$end
#0
$dumpvars
b0 "
b0 !
$end
#2
b1111110 "
b1 !
#4
b110000 "
b10 !
#6
b1111001 "
b11 !
#8
b110011 "
b100 !
#10
b1011011 "
b101 !
#12
b1011111 "
b110 !
#14
b1110000 "
b111 !
#16
b1111111 "
b1000 !
#18
b1111011 "
b1001 !
#20
b1110111 "
b1010 !
#22
b11111 "
b1011 !
#24
b1001110 "
b1100 !
#26
b111101 "
b1101 !
#28
b1001111 "
b1110 !
#30
b1000111 "
b1111 !
