SPRINT3/RegisterFile.sv
module RegisterFile #(parameter N = 8)
        (input  logic [N-1:0] wd3,
         input  logic [2:0] wa3, ra1, ra2,
         input  logic we3, clk, rst,
         output logic [N-1:0] rd1, rd2);
         // ra1 e ra2 são os seletores do mux, ra1 disponibilizando a saí­da no rd1 e ra2 a no rd2.

    // 8 registradores de 8 bits
    logic  [N-1:0] registradores[N-1:0];

    // OBS: O registrador $0 é somente de LEITURA e seu valor deve ser fixo em ZERO.
    initial registradores[0] = 0;

    // Escrita nos registradores dependendo do clock.
    always@(posedge clk)
        begin
            if (wa3 && we3) registradores[wa3] <= wd3;
            if ( !rst )
            begin
                registradores[0] <= 0;	registradores[1] <= 0;	
                registradores[2] <= 0;	registradores[3] <= 0;	
                registradores[4] <= 0;	registradores[5] <= 0;	
                registradores[6] <= 0;	registradores[7] <= 0;	
            end
        end

    // Leitura dos valores dos registradores
    assign rd1 = registradores[ra1];
    assign rd2 = registradores[ra2];

endmodule


module tb_RegisterFile;

    // Inputs
    logic [7:0] wd3;
    logic [2:0] wa3, ra1, ra2;
    logic we3, clk, rst;
    //Outputs
    logic [7:0] rd1, rd2;

    RegisterFile #(.N(8)) register( .wd3( wd3 ), .wa3( wa3 ), .ra1( ra1 ), .ra2( ra2 ), 
								    .we3( we3 ), .clk( clk ), .rst( rst ), .rd1( rd1 ), 
								    .rd2( rd2 ));

    initial
        begin
             wd3 = 0;
             wa3 = 0;
             ra1 = 0;
             ra2 = 0;
             we3 = 0;
             rst = 1;   
             clk = 0;     
        end

    always #1 clk = ~clk;

    initial begin

        we3 = 1;
        wa3 = 1;
        #1 wd3 = 8'hab;
        #1 wa3 = 4;
        wd3 = 8'hff;
        ra1 = 1;
        #3 ra2 = 4;
        #3 wa3 = 5;
        wd3 = 8'haf;
        ra1 = 5;
        ra2 = 1;
        #5 rst = 0;

    end

    initial

        begin
            $dumpfile("RegisterFile.vcd");
            $dumpvars(0, register);
        end

    initial 
        #25 $finish;

endmodule

/*  Para 32bits:
    N = 32 bits
    [5:0] wa3, ra1, ra2;
*/

/* Menor quantidade de linhas

    logic [N-1:0] registradores[N-1:0];
    initial registradores[0] = 0;
    always@(posedge clk, negedge rst) if (wa3 && we3) registradores[wa3] <= wd3; 
    if ( !rst ) begin
                registradores[0] <= 0;	registradores[1] <= 0;	
                registradores[2] <= 0;	registradores[3] <= 0;	
                registradores[4] <= 0;	registradores[5] <= 0;	
                registradores[6] <= 0;	registradores[7] <= 0;	
                end
    assign rd1 = registradores[ra1];
    assign rd2 = registradores[ra2];

*/

SPRINT3/RegisterFile.vcd
$date
	Wed Apr 12 22:32:10 2023
$end
$version
	Icarus Verilog
$end
$timescale
	1s
$end
$scope module tb_RegisterFile $end
$scope module register $end
$var wire 1 ! clk $end
$var wire 3 " ra1 [2:0] $end
$var wire 3 # ra2 [2:0] $end
$var wire 8 $ rd1 [7:0] $end
$var wire 8 % rd2 [7:0] $end
$var wire 1 & rst $end
$var wire 3 ' wa3 [2:0] $end
$var wire 8 ( wd3 [7:0] $end
$var wire 1 ) we3 $end
$var parameter 32 * N $end
$upscope $end
$upscope $end
$enddefinitions $end
$comment Show the parameter values. $end
$dumpall
b1000 *
$end
#0
$dumpvars
1)
b0 (
b1 '
1&
b0 %
b0 $
b0 #
b0 "
0!
$end
#1
b10101011 (
1!
#2
b10101011 $
b1 "
b11111111 (
b100 '
0!
#3
1!
#4
0!
#5
1!
b11111111 %
b100 #
#6
0!
#7
1!
#8
0!
b10101011 %
b1 #
bx $
b101 "
b10101111 (
b101 '
#9
b10101111 $
1!
#10
0!
#11
1!
#12
0!
#13
b0 $
b0 %
1!
0&
#14
0!
#15
b0 $
1!
#16
0!
#17
b0 $
1!
#18
0!
#19
b0 $
1!
#20
0!
#21
b0 $
1!
#22
0!
#23
b0 $
1!
#24
0!
#25
b0 $
1!
